{
  "url": "/users/password",
  "content_file": "",
  "type": "POST",
  "query_params": "",
  "status_code": 302,
  "headers": {
    "Server": "nginx",
    "Content-Type": "text/html; charset=utf-8",
    "Connection": "keep-alive",
    "Cache-Control": "no-cache",
    "Location": "http://{ADDR}:{PORT}/users/sign_in",
    "X-Gitlab-Meta": "{\"correlation_id\":\"01HYS2FZ0W195ZZD0TF1DW0E40\",\"version\":\"1\"}",
    "X-Request-Id": "01HYS2FZ0W195ZZD0TF1DW0E40",
    "X-Runtime": "0.020184",
    "Strict-Transport-Security": "max-age=63072000",
    "Referrer-Policy": "strict-origin-when-cross-origin"
  }
}